awslabs/__init__.py
awslabs/syntheticdata_mcp_server/__init__.py
awslabs/syntheticdata_mcp_server/pandas_interpreter.py
awslabs/syntheticdata_mcp_server/server.py
awslabs/syntheticdata_mcp_server/storage/__init__.py
awslabs/syntheticdata_mcp_server/storage/base.py
awslabs/syntheticdata_mcp_server/storage/loader.py
awslabs/syntheticdata_mcp_server/storage/s3.py
awslabs_syntheticdata_mcp_server-1.0.11.dist-info/METADATA
awslabs_syntheticdata_mcp_server-1.0.11.dist-info/WHEEL
awslabs_syntheticdata_mcp_server-1.0.11.dist-info/entry_points.txt
awslabs_syntheticdata_mcp_server-1.0.11.dist-info/licenses/LICENSE
awslabs_syntheticdata_mcp_server-1.0.11.dist-info/licenses/NOTICE
awslabs_syntheticdata_mcp_server-1.0.11.dist-info/RECORD
