Metadata-Version: 2.4
Name: awslabs.syntheticdata-mcp-server
Version: 1.0.11
Summary: An AWS Labs Model Context Protocol (MCP) server for syntheticdata
Project-URL: homepage, https://awslabs.github.io/mcp/
Project-URL: docs, https://awslabs.github.io/mcp/servers/syntheticdata-mcp-server/
Project-URL: documentation, https://awslabs.github.io/mcp/servers/syntheticdata-mcp-server/
Project-URL: repository, https://github.com/awslabs/mcp.git
Project-URL: changelog, https://github.com/awslabs/mcp/blob/main/src/syntheticdata-mcp-server/CHANGELOG.md
Author: Amazon Web Services
Author-email: AWSLabs MCP <203918161+awslabs-mcp@users.noreply.github.com>
License: Apache-2.0
License-File: LICENSE
License-File: NOTICE
Classifier: License :: OSI Approved :: Apache Software License
Classifier: Operating System :: OS Independent
Classifier: Programming Language :: Python
Classifier: Programming Language :: Python :: 3
Classifier: Programming Language :: Python :: 3.10
Classifier: Programming Language :: Python :: 3.11
Classifier: Programming Language :: Python :: 3.12
Classifier: Programming Language :: Python :: 3.13
Requires-Python: >=3.10
Requires-Dist: boto3>=1.34.0
Requires-Dist: mcp[cli]>=1.23.0
Requires-Dist: pandas>=2.0.0
Requires-Dist: pyarrow>=14.0.1
Requires-Dist: pydantic>=2.10.6
Requires-Dist: python-snappy>=0.6.1
